docs/Makefile
docs/make.bat
docs/source/conf.py
docs/source/howto.rst
docs/source/index.rst
docs/source/intro.rst
docs/source/_static/github-logo.svg
docs/source/howtos/1 Validating Scenes.rst
docs/source/howtos/2 Converting Files.rst
raillabel_providerkit/__init__.py
raillabel_providerkit/__main__.py
raillabel_providerkit/exceptions.py
raillabel_providerkit/_util/__init__.py
raillabel_providerkit/_util/_attribute_type.py
raillabel_providerkit/_util/_sensor_metadata.py
raillabel_providerkit/_util/_warning.py
raillabel_providerkit/convert/__init__.py
raillabel_providerkit/convert/convert.py
raillabel_providerkit/convert/translation.json
raillabel_providerkit/convert/translation.json.license
raillabel_providerkit/convert/loader_classes/__init__.py
raillabel_providerkit/convert/loader_classes/_loader_abc.py
raillabel_providerkit/convert/loader_classes/loader_understand_ai.py
raillabel_providerkit/format/__init__.py
raillabel_providerkit/format/raillabel_schema.json
raillabel_providerkit/format/raillabel_schema.json.license
raillabel_providerkit/format/understand_ai_t4_schema.json
raillabel_providerkit/format/understand_ai_t4_schema.json.license
raillabel_providerkit/format/understand_ai/__init__.py
raillabel_providerkit/format/understand_ai/_annotation.py
raillabel_providerkit/format/understand_ai/_translation.py
raillabel_providerkit/format/understand_ai/bounding_box_2d.py
raillabel_providerkit/format/understand_ai/bounding_box_3d.py
raillabel_providerkit/format/understand_ai/coordinate_system.py
raillabel_providerkit/format/understand_ai/frame.py
raillabel_providerkit/format/understand_ai/metadata.py
raillabel_providerkit/format/understand_ai/point_3d.py
raillabel_providerkit/format/understand_ai/polygon_2d.py
raillabel_providerkit/format/understand_ai/polyline_2d.py
raillabel_providerkit/format/understand_ai/quaternion.py
raillabel_providerkit/format/understand_ai/scene.py
raillabel_providerkit/format/understand_ai/segmentation_3d.py
raillabel_providerkit-1.4.0.dist-info/licenses/LICENSE
raillabel_providerkit-1.4.0.dist-info/METADATA
raillabel_providerkit-1.4.0.dist-info/WHEEL
raillabel_providerkit-1.4.0.dist-info/top_level.txt
raillabel_providerkit-1.4.0.dist-info/RECORD
