Metadata-Version: 2.4
Name: raillabel-providerkit
Version: 1.4.0
Summary: A devkit for working with recorded and annotated train ride data from Deutsche Bahn.
Author: DB InfraGO AG
License: Apache-2.0
Project-URL: Homepage, https://github.com/dbinfrago/raillabel-providerkit
Project-URL: Documentation, https://dbinfrago.github.io/raillabel-providerkit
Platform: any
Classifier: Development Status :: 1 - Planning
Classifier: License :: OSI Approved :: Apache Software License
Classifier: Natural Language :: English
Classifier: Operating System :: OS Independent
Classifier: Programming Language :: Python :: 3 :: Only
Classifier: Programming Language :: Python :: 3.10
Classifier: Programming Language :: Python :: 3.11
Classifier: Programming Language :: Python :: 3.12
Classifier: Programming Language :: Python :: 3.13
Requires-Python: <3.14,>=3.10
License-File: LICENSE
Requires-Dist: jsonschema>=4.4.0
Requires-Dist: fastjsonschema>=2.16.2
Requires-Dist: raillabel==4.1.1
Requires-Dist: pyyaml>=6.0.0
Requires-Dist: numpy>=1.24.4
Requires-Dist: scipy>=1.14.1
Requires-Dist: pydantic<3.0.0
Requires-Dist: tqdm>=4.63.0
Requires-Dist: click>=8.1.8
Provides-Extra: docs
Requires-Dist: furo; extra == "docs"
Requires-Dist: sphinx; extra == "docs"
Requires-Dist: sphinx-copybutton; extra == "docs"
Requires-Dist: tomli; python_version < "3.14" and extra == "docs"
Provides-Extra: test
Requires-Dist: pytest; extra == "test"
Requires-Dist: pytest-cov; extra == "test"
Requires-Dist: json5; extra == "test"
Dynamic: license-file
